{
    "servers": {
        "msx-crm": {
            "type": "stdio",
            "command": "node",
            "args": [
                "${workspaceFolder}/src/index.js"
            ],
            "env": {
                "MSX_CRM_URL": "https://microsoftsales.crm.dynamics.com",
                "MSX_TENANT_ID": "72f988bf-86f1-41af-91ab-2d7cd011db47"
            }
        },
        "workiq": {
            "command": "npx",
            "args": [
                "-y",
                "@microsoft/workiq",
                "mcp"
            ],
            "tools": [
                "*"
            ]
        }
    }
}